nelsonsiegel/__init__.py
nelsonsiegel/base.py
nelsonsiegel-0.1.1.dist-info/LICENSE
nelsonsiegel-0.1.1.dist-info/METADATA
nelsonsiegel-0.1.1.dist-info/WHEEL
nelsonsiegel-0.1.1.dist-info/top_level.txt
nelsonsiegel-0.1.1.dist-info/RECORD
