Metadata-Version: 2.1
Name: nelsonsiegel
Version: 0.1.1
Summary: Suites for Nelson-Siegel style yield curve fitting.
Home-page: http://github.com/linxichen/nelsonsiegel
Author: Linxi Chen
Author-email: linxichen88@gmail.com
License: GPL v3
Platform: UNKNOWN
Requires-Dist: numpy
Requires-Dist: pandas
Requires-Dist: scikit-learn
